[
    {
        "count": 1,
        "FScore": 0.5816666666666667
    },
    {
        "count": 2,
        "FScore": 0.47385823161996443
    },
    {
        "count": 3,
        "FScore": 0.3972891029070804
    },
    {
        "count": 4,
        "FScore": 0.36545269975502537
    },
    {
        "count": 5,
        "FScore": 0.3242535242535243
    },
    {
        "count": 6,
        "FScore": 0.309344444490888
    },
    {
        "count": 7,
        "FScore": 0.25180408738548277
    },
    {
        "count": 8,
        "FScore": 0.24003447201416742
    },
    {
        "count": 9,
        "FScore": 0.2258377611399589
    },
    {
        "count": 10,
        "FScore": 0.21207727846383312
    },
    {
        "count": 11,
        "FScore": 0.18348049131631222
    },
    {
        "count": 12,
        "FScore": 0.1740313531054318
    },
    {
        "count": 13,
        "FScore": 0.16391846968672527
    },
    {
        "count": 14,
        "FScore": 0.14925669614250928
    },
    {
        "count": 15,
        "FScore": 0.1415569318959238
    },
    {
        "count": 16,
        "FScore": 0.13347125658825007
    },
    {
        "count": 17,
        "FScore": 0.13196139699899098
    },
    {
        "count": 18,
        "FScore": 0.13050266945003786
    },
    {
        "count": 19,
        "FScore": 0.12407440504375644
    },
    {
        "count": 20,
        "FScore": 0.11451819785153118
    },
    {
        "count": 21,
        "FScore": 0.08695652173913043
    },
    {
        "count": 22,
        "FScore": 0.07608695652173914
    },
    {
        "count": 23,
        "FScore": 0.07222222222222222
    },
    {
        "count": 24,
        "FScore": 0.05999999999999999
    },
    {
        "count": 25,
        "FScore": 0.05128205128205129
    },
    {
        "count": 26,
        "FScore": 0.07407407407407407
    }
]
