[
    {
        "count": 1,
        "FScore": 0.6560344827586206
    },
    {
        "count": 2,
        "FScore": 0.562718468855653
    },
    {
        "count": 3,
        "FScore": 0.47995362939183167
    },
    {
        "count": 4,
        "FScore": 0.42587782587782586
    },
    {
        "count": 5,
        "FScore": 0.37851738904370485
    },
    {
        "count": 6,
        "FScore": 0.35051285302331325
    },
    {
        "count": 7,
        "FScore": 0.2951750058726803
    },
    {
        "count": 8,
        "FScore": 0.2759382185778125
    },
    {
        "count": 9,
        "FScore": 0.25462033387857563
    },
    {
        "count": 10,
        "FScore": 0.23257086355369147
    },
    {
        "count": 11,
        "FScore": 0.20326891185100143
    },
    {
        "count": 12,
        "FScore": 0.19351986190845674
    },
    {
        "count": 13,
        "FScore": 0.17996937280659395
    },
    {
        "count": 14,
        "FScore": 0.16399141355888758
    },
    {
        "count": 15,
        "FScore": 0.15347218488850659
    },
    {
        "count": 16,
        "FScore": 0.1442677967219531
    },
    {
        "count": 17,
        "FScore": 0.13598661155052133
    },
    {
        "count": 18,
        "FScore": 0.1303604219393693
    },
    {
        "count": 19,
        "FScore": 0.1223569967689711
    },
    {
        "count": 20,
        "FScore": 0.11253407086740419
    },
    {
        "count": 21,
        "FScore": 0.08332015810276677
    },
    {
        "count": 22,
        "FScore": 0.07065217391304349
    },
    {
        "count": 23,
        "FScore": 0.06666666666666667
    },
    {
        "count": 24,
        "FScore": 0.05999999999999999
    },
    {
        "count": 25,
        "FScore": 0.05128205128205129
    },
    {
        "count": 26,
        "FScore": 0.07407407407407407
    }
]
